pyvatsim/__init__.py
pyvatsim/liveapi.py
pyvatsim-0.1.2.dist-info/METADATA
pyvatsim-0.1.2.dist-info/WHEEL
pyvatsim-0.1.2.dist-info/licenses/LICENSE
pyvatsim-0.1.2.dist-info/RECORD
