Metadata-Version: 2.1
Name: pyvatsim
Version: 0.1.2
Summary: Library to access Vatsim live data and APIs
Project-URL: Homepage, https://github.com/kengreim/Vatsim-Py-API
Project-URL: Bug Tracker, https://github.com/kengreim/Vatsim-Py-API/issues
Author-email: Ken Greim <ken.greim+vatsimapi@gmail.com>
License-File: LICENSE
Classifier: Development Status :: 3 - Alpha
Classifier: Intended Audience :: Developers
Classifier: License :: OSI Approved :: MIT License
Classifier: Operating System :: OS Independent
Classifier: Programming Language :: Python :: 3
Classifier: Topic :: Games/Entertainment :: Simulation
Classifier: Topic :: Software Development :: Libraries :: Python Modules
Requires-Python: >=3.10
Requires-Dist: requests>=2.28
